h5pydantic/__init__.py
h5pydantic/enum.py
h5pydantic/model.py
h5pydantic/newsfragments/.gitignore
h5pydantic/newsfragments/multi.feature
h5pydantic/types.py
h5pydantic-0.4.0.dist-info/METADATA
h5pydantic-0.4.0.dist-info/WHEEL
h5pydantic-0.4.0.dist-info/RECORD
