Metadata-Version: 2.1
Name: h5pydantic
Version: 0.4.0
Summary: Pydantic models for HDF5 files.
Home-page: https://gitlab.com/clinton.roy/h5pydantic
Author: Clinton Roy
Author-email: clinton.roy@gmail.com
Requires-Python: >=3.9,<4.0
Classifier: Development Status :: 3 - Alpha
Classifier: Framework :: Pydantic
Classifier: Intended Audience :: Science/Research
Classifier: License :: OSI Approved :: Python Software Foundation License
Classifier: Natural Language :: English
Classifier: Programming Language :: Python :: 3
Classifier: Programming Language :: Python :: 3.9
Classifier: Programming Language :: Python :: 3.10
Classifier: Programming Language :: Python :: 3.11
Classifier: Topic :: File Formats
Classifier: Topic :: Scientific/Engineering :: Information Analysis
Requires-Dist: h5py (>=3.8.0,<4.0.0)
Requires-Dist: pydantic (>=1.10.7,<2.0.0)
Requires-Dist: typing-extensions (>=4.6.3,<5.0.0)
Project-URL: Documentation, https://h5pydantic.readthedocs.io/
Project-URL: Repository, https://gitlab.com/clinton.roy/h5pydantic
